cli/__init__.py
cli/action.py
cli/analysis.py
cli/arg_parser.py
cli/auth.py
cli/cli.py
cli/clone.py
cli/label.py
cli/utils.py
depmap-0.4.11.dist-info/METADATA
depmap-0.4.11.dist-info/WHEEL
depmap-0.4.11.dist-info/entry_points.txt
depmap-0.4.11.dist-info/top_level.txt
depmap-0.4.11.dist-info/RECORD
