Metadata-Version: 2.1
Name: depmap
Version: 0.4.11
Summary: Dependency Mapper CLI for managing and analyzing software dependencies across repositories.
Home-page: https://github.com/trilogy-group/central-product-tpm/tree/master/POC/cc/repo/depmap/cli
Author: David Schwartz
Author-email: david.schwartz@devfactory.com
Classifier: Programming Language :: Python :: 3.9
Classifier: License :: OSI Approved :: MIT License
Classifier: Operating System :: OS Independent
Requires-Python: >=3.9
Requires-Dist: tqdm
Requires-Dist: boto3
Requires-Dist: requests
Requires-Dist: pygments
Requires-Dist: python-dotenv
